CHANGES.rst
MANIFEST.in
README.rst
setup.py
timeout_decorator/__init__.py
timeout_decorator/timeout_decorator.py
timeout_decorator.egg-info/PKG-INFO
timeout_decorator.egg-info/SOURCES.txt
timeout_decorator.egg-info/dependency_links.txt
timeout_decorator.egg-info/top_level.txt