Metadata-Version: 1.1
Name: timeout-decorator
Version: 0.3.0
Summary: Timeout decorator
Home-page: https://github.com/pnpnpn/timeout-decorator
Author: Patrick Ng
Author-email: pn.appdev@gmail.com
License: UNKNOWN
Platform: UNKNOWN
Classifier: Development Status :: 4 - Beta
Classifier: Intended Audience :: Developers
Classifier: License :: OSI Approved :: MIT License
Classifier: Natural Language :: English
Classifier: Operating System :: OS Independent
Classifier: Programming Language :: Python
Classifier: Topic :: Software Development :: Libraries :: Python Modules
